{
  "Datetime": "2018-03-11T18:37:54Z",
  "1": {
    "Address": "176.9.68.110",
    "Name": "HugeAlice2",
    "Status": "Active",
    "Version": "0.6.95-BETA",
    "Uptime": 3054420
  },
  "2": {
    "Address": "176.9.20.180",
    "Name": "HugeAlice3",
    "Status": "Active",
    "Version": "0.6.95-BETA",
    "Uptime": 3054391
  },
  "3": {
    "Address": "199.217.118.114",
    "Name": "HugeAlice4",
    "Status": "Active",
    "Version": "0.6.95-BETA",
    "Uptime": 3054456
  },
  "4": {
    "Address": "108.61.182.27",
    "Name": "Alice5",
    "Status": "Active",
    "Version": "0.6.95-BETA",
    "Uptime": 2977818
  },
  "5": {
    "Address": "108.61.168.86",
    "Name": "Alice6",
    "Status": "Active",
    "Version": "0.6.95-BETA",
    "Uptime": 2977717
  },
  "6": {
    "Address": "104.238.161.61",
    "Name": "Alice7",
    "Status": "Active",
    "Version": "0.6.95-BETA",
    "Uptime": 2977690
  },
  "7": {
    "Address": "88.99.192.82",
    "Name": "HugeAlice",
    "Status": "Active",
    "Version": "0.6.95-BETA",
    "Uptime": 3054451
  },
  "8": {
    "Address": "san.nem.ninja",
    "Name": "san",
    "Status": "Active",
    "Version": "0.6.95-BETA",
    "Uptime": 3401128
  },
  "9": {
    "Address": "go.nem.ninja",
    "Name": "go",
    "Status": "Active",
    "Version": "0.6.95-BETA",
    "Uptime": 3401111
  },
  "10": {
    "Address": "hachi.nem.ninja",
    "Name": "hachi",
    "Status": "Active",
    "Version": "0.6.95-BETA",
    "Uptime": 3401090
  }
}
